.long-description.html
README.rst
setup.py
src/Products/__init__.py
src/Products.PFGSelectionStringField.egg-info/PKG-INFO
src/Products.PFGSelectionStringField.egg-info/SOURCES.txt
src/Products.PFGSelectionStringField.egg-info/dependency_links.txt
src/Products.PFGSelectionStringField.egg-info/entry_points.txt
src/Products.PFGSelectionStringField.egg-info/namespace_packages.txt
src/Products.PFGSelectionStringField.egg-info/not-zip-safe
src/Products.PFGSelectionStringField.egg-info/requires.txt
src/Products.PFGSelectionStringField.egg-info/top_level.txt
src/Products/PFGSelectionStringField/__init__.py
src/Products/PFGSelectionStringField/configure.zcml
src/Products/PFGSelectionStringField/interfaces.py
src/Products/PFGSelectionStringField/skins.zcml
src/Products/PFGSelectionStringField/content/__init__.py
src/Products/PFGSelectionStringField/content/configure.zcml
src/Products/PFGSelectionStringField/content/field.py
src/Products/PFGSelectionStringField/docs/CONTRIBUTORS.rst
src/Products/PFGSelectionStringField/docs/CREDITS.rst
src/Products/PFGSelectionStringField/docs/HISTORY.rst
src/Products/PFGSelectionStringField/docs/INSTALL.rst
src/Products/PFGSelectionStringField/docs/LICENSE.rst
src/Products/PFGSelectionStringField/docs/Makefile
src/Products/PFGSelectionStringField/docs/README.rst
src/Products/PFGSelectionStringField/docs/conf.py
src/Products/PFGSelectionStringField/docs/index.rst
src/Products/PFGSelectionStringField/docs/_static/.gitignore
src/Products/PFGSelectionStringField/locales/Products.PFGSelectionStringField.pot
src/Products/PFGSelectionStringField/locales/fi/LC_MESSAGES/Products.PFGSelectionStringField.po
src/Products/PFGSelectionStringField/profiles/default/factorytool.xml
src/Products/PFGSelectionStringField/profiles/default/metadata.xml
src/Products/PFGSelectionStringField/profiles/default/propertiestool.xml
src/Products/PFGSelectionStringField/profiles/default/rolemap.xml
src/Products/PFGSelectionStringField/profiles/default/skins.xml
src/Products/PFGSelectionStringField/profiles/default/types.xml
src/Products/PFGSelectionStringField/profiles/default/workflows.xml
src/Products/PFGSelectionStringField/profiles/default/types/FormFolder.xml
src/Products/PFGSelectionStringField/profiles/default/types/PFGSelectionStringField.xml
src/Products/PFGSelectionStringField/skins/PFGSelectionStringField/selection_string.pt
src/Products/PFGSelectionStringField/tests/__init__.py
src/Products/PFGSelectionStringField/tests/base.py
