Metadata-Version: 1.1
Name: Products.PFGSelectionStringField
Version: 2.6
Summary: Adds selection field type with string field to Products.PloneFormGen.
Home-page: https://github.com/collective/Products.PFGSelectionStringField
Author: Taito Horiuchi
Author-email: taito.horiuchi@gmail.com
License: BSD
Platform: UNKNOWN
Classifier: Framework :: Plone
Classifier: Framework :: Plone :: 4.3
Classifier: License :: OSI Approved :: BSD License
Classifier: Programming Language :: Python
Classifier: Programming Language :: Python :: 2.7
